pycert/__init__.py
pycert-1.0.4.dist-info/LICENSE
pycert-1.0.4.dist-info/METADATA
pycert-1.0.4.dist-info/WHEEL
pycert-1.0.4.dist-info/top_level.txt
pycert-1.0.4.dist-info/RECORD
