Metadata-Version: 2.1
Name: pycert
Version: 1.0.4
Summary: The cross-platform tool to get certificate info (including self-signed).
Home-page: https://github.com/c-pher/certificate
Author: Andrey Komissarov
Author-email: a.komisssarov@gmail.com
License: GNU General Public License v3.0
Classifier: Programming Language :: Python :: 3
Classifier: License :: OSI Approved :: GNU General Public License v3 (GPLv3)
Classifier: Operating System :: OS Independent
Requires-Python: >=3.6
License-File: LICENSE
Requires-Dist: pyOpenSSL (>=21.0.0)
Requires-Dist: python-dateutil (~=2.8.2)
Requires-Dist: plogger (>=1.0.6)
